ieforms/__init__.py
ieforms/constants.py
ieforms/fields.py
ieforms/widgets.py
ieforms-1.0.1.dist-info/licenses/LICENSE
ieforms-1.0.1.dist-info/METADATA
ieforms-1.0.1.dist-info/WHEEL
ieforms-1.0.1.dist-info/top_level.txt
ieforms-1.0.1.dist-info/RECORD
