Metadata-Version: 2.4
Name: ieforms
Version: 1.0.1
Summary: Django form fields for Irish Eircodes and Counties.
Home-page: https://github.com/MohanKumarMakesh/ieforms
Author: Your Name
Author-email: 
License: MIT
Classifier: Development Status :: 5 - Production/Stable
Classifier: Framework :: Django
Classifier: License :: OSI Approved :: MIT License
Classifier: Programming Language :: Python :: 3
License-File: LICENSE
Requires-Dist: Django>=3.2
Dynamic: author
Dynamic: classifier
Dynamic: description
Dynamic: description-content-type
Dynamic: home-page
Dynamic: license
Dynamic: license-file
Dynamic: requires-dist
Dynamic: summary
